pytest_leak_finder.py
pytest_leak_finder-0.3.0.dist-info/METADATA
pytest_leak_finder-0.3.0.dist-info/WHEEL
pytest_leak_finder-0.3.0.dist-info/entry_points.txt
pytest_leak_finder-0.3.0.dist-info/licenses/LICENSE
pytest_leak_finder-0.3.0.dist-info/RECORD
