Metadata-Version: 2.4
Name: pytest-leak-finder
Version: 0.3.0
Summary: Find the test that's leaking before the one that fails
Project-URL: homepage, https://github.com/mgaitan/pytest-leak-finder
Author-email: Martín Gaitán <gaitan@gmail.com>
License: MIT
License-File: LICENSE
Keywords: pytest,testing
Classifier: Development Status :: 4 - Beta
Classifier: Framework :: Pytest
Classifier: Intended Audience :: Developers
Classifier: License :: OSI Approved :: MIT License
Classifier: Operating System :: OS Independent
Classifier: Programming Language :: Python
Classifier: Programming Language :: Python :: 3
Classifier: Programming Language :: Python :: 3.10
Classifier: Programming Language :: Python :: 3.11
Classifier: Programming Language :: Python :: 3.12
Classifier: Programming Language :: Python :: 3.13
Classifier: Programming Language :: Python :: 3.14
Classifier: Programming Language :: Python :: Implementation :: CPython
Classifier: Programming Language :: Python :: Implementation :: PyPy
Classifier: Topic :: Software Development :: Testing
Requires-Python: >=3.10
Requires-Dist: pytest>=3.5.0
